README.rst
clamav.py
setup.py
clamav.egg-info/PKG-INFO
clamav.egg-info/SOURCES.txt
clamav.egg-info/dependency_links.txt
clamav.egg-info/requires.txt
clamav.egg-info/top_level.txt