Metadata-Version: 1.1
Name: clamav
Version: 0.1
Summary: A Python interface to ClamAV.
Home-page: UNKNOWN
Author: Ryan Gonzalez
Author-email: kirbyfan64sos@gmail.com
License: UNKNOWN
Platform: UNKNOWN
Classifier: License :: OSI Approved :: BSD License
Classifier: Programming Language :: Python :: 2
Classifier: Programming Language :: Python :: 3
Requires: cffi
